nonebot_plugin_bing_chat/__init__.py
nonebot_plugin_bing_chat/common/__init__.py
nonebot_plugin_bing_chat/common/data_model.py
nonebot_plugin_bing_chat/common/exceptions.py
nonebot_plugin_bing_chat/common/utils.py
nonebot_plugin_bing_chat/onebotv11/check.py
nonebot_plugin_bing_chat/onebotv11/main.py
nonebot_plugin_bing_chat/onebotv11/utils.py
nonebot_plugin_bing_chat/onebotv12/main.py
nonebot_plugin_bing_chat/telegram/main.py
nonebot_plugin_bing_chat-0.7.10.dist-info/LICENSE
nonebot_plugin_bing_chat-0.7.10.dist-info/METADATA
nonebot_plugin_bing_chat-0.7.10.dist-info/WHEEL
nonebot_plugin_bing_chat-0.7.10.dist-info/top_level.txt
nonebot_plugin_bing_chat-0.7.10.dist-info/RECORD
