Metadata-Version: 2.1
Name: nonebot-plugin-bing-chat
Version: 0.7.10
Summary: 基于nonebot2的bing-chat软件
Author-email: Harry <Harry0259@163.com>
License: GPL-3
Project-URL: Homepage, https://github.com/Harry-Jing/nonebot-plugin-bing-chat
Classifier: Framework :: Pydantic
Classifier: Topic :: Communications
Classifier: License :: OSI Approved :: GNU General Public License (GPL)
Classifier: License :: OSI Approved :: GNU General Public License v3 (GPLv3)
Classifier: Programming Language :: Python :: 3
Classifier: Programming Language :: Python :: 3 :: Only
Classifier: Programming Language :: Python :: 3.10
Classifier: Programming Language :: Python :: 3.11
Classifier: Natural Language :: Chinese (Simplified)
Requires-Python: >=3.10
License-File: LICENSE
Requires-Dist: EdgeGPT (>=0.1.20)
Requires-Dist: nonebot2 (>=2.0.0rc3)
Requires-Dist: nonebot-adapter-onebot (>=2.2.2)
Requires-Dist: nonebot-plugin-apscheduler (>=0.2.0)
Requires-Dist: nonebot-plugin-guild-patch (>=0.2.3)
Requires-Dist: pydantic (>=1.10.7)
Provides-Extra: all
Requires-Dist: nonebot-plugin-htmlrender (>=0.2.0.3) ; extra == 'all'
Provides-Extra: image
Requires-Dist: nonebot-plugin-htmlrender (>=0.2.0.3) ; extra == 'image'
